MANIFEST.in
setup.py
zuora/__init__.py
zuora/client.py
zuora/rest_client.py
zuora/tests.py
zuora/zuora.a.43.0.dev.wsdl
zuora/zuora.a.43.0.wsdl
zuora/zuora.a.48.0.dev.wsdl
zuora/zuora.a.48.0.wsdl
zuora.egg-info/PKG-INFO
zuora.egg-info/SOURCES.txt
zuora.egg-info/dependency_links.txt
zuora.egg-info/not-zip-safe
zuora.egg-info/pbr.json
zuora.egg-info/requires.txt
zuora.egg-info/top_level.txt
zuora/./zuora.a.43.0.dev.wsdl
zuora/./zuora.a.43.0.wsdl
zuora/./zuora.a.48.0.dev.wsdl
zuora/./zuora.a.48.0.wsdl
zuora/rest_wrapper/__init__.py
zuora/rest_wrapper/account_manager.py
zuora/rest_wrapper/catalog_manager.py
zuora/rest_wrapper/functional_tests.py
zuora/rest_wrapper/payment_method_manager.py
zuora/rest_wrapper/request_base.py
zuora/rest_wrapper/subscription_manager.py
zuora/rest_wrapper/transaction_manager.py
zuora/rest_wrapper/usage_manager.py