Metadata-Version: 1.0
Name: zuora
Version: 1.0.17
Summary: Zuora client library.
Home-page: http://github.com/mapmyfitness/python-zuora
Author: MapMyFitness
Author-email: brandon.fredericks@mapmyfitness.com
License: UNKNOWN
Platform: UNKNOWN
